{
  "schema_version": 1,
  "plan_id": "caduceus-v0.1",
  "tasks": {
    "0.1": {
      "status": "complete",
      "updated_at": "2026-07-13T14:02:04.412675+00:00",
      "handoff": "handoffs/0.1.md"
    },
    "0.2": {
      "status": "complete",
      "updated_at": "2026-07-13T14:48:19.074620+00:00",
      "handoff": "handoffs/0.2.md"
    },
    "1.1": {
      "status": "complete",
      "updated_at": "2026-07-13T15:13:01.275564+00:00",
      "handoff": "handoffs/1.1.md"
    },
    "1.2": {
      "status": "complete",
      "updated_at": "2026-07-13T15:21:26.625372+00:00",
      "handoff": "handoffs/1.2.md"
    },
    "1.3": {
      "status": "complete",
      "updated_at": "2026-07-13T15:30:36.737277+00:00",
      "handoff": "handoffs/1.3.md"
    },
    "1.4": {
      "status": "complete",
      "updated_at": "2026-07-13T15:50:12.246698+00:00",
      "handoff": "handoffs/1.4.md"
    },
    "1.5": {
      "status": "complete",
      "updated_at": "2026-07-13T16:08:42.108505+00:00",
      "handoff": "handoffs/1.5.md"
    },
    "1.6": {
      "status": "complete",
      "updated_at": "2026-07-13T16:23:22.466986+00:00",
      "handoff": "handoffs/1.6.md"
    },
    "2.1": {
      "status": "complete",
      "updated_at": "2026-07-13T22:06:44.613980+00:00",
      "handoff": "handoffs/2.1.md"
    },
    "2.2": {
      "status": "complete",
      "updated_at": "2026-07-13T22:21:55.212638+00:00",
      "handoff": "handoffs/2.2.md"
    },
    "2.3": {
      "status": "complete",
      "updated_at": "2026-07-13T22:30:04.588220+00:00",
      "handoff": "handoffs/2.3.md"
    },
    "2.4": {
      "status": "pending",
      "updated_at": null,
      "handoff": null
    },
    "2.5": {
      "status": "pending",
      "updated_at": null,
      "handoff": null
    },
    "2.6": {
      "status": "pending",
      "updated_at": null,
      "handoff": null
    },
    "3.0": {
      "status": "complete",
      "updated_at": "2026-07-13T16:29:42.220493+00:00",
      "handoff": "handoffs/3.0.md"
    },
    "3.1": {
      "status": "pending",
      "updated_at": null,
      "handoff": null
    },
    "3.2": {
      "status": "pending",
      "updated_at": null,
      "handoff": null
    },
    "3.3": {
      "status": "pending",
      "updated_at": null,
      "handoff": null
    },
    "3.4": {
      "status": "pending",
      "updated_at": null,
      "handoff": null
    },
    "4.1": {
      "status": "pending",
      "updated_at": null,
      "handoff": null
    },
    "4.2": {
      "status": "pending",
      "updated_at": null,
      "handoff": null
    },
    "4.3": {
      "status": "pending",
      "updated_at": null,
      "handoff": null
    },
    "4.4": {
      "status": "pending",
      "updated_at": null,
      "handoff": null
    },
    "4.5": {
      "status": "pending",
      "updated_at": null,
      "handoff": null
    },
    "5.0": {
      "status": "pending",
      "updated_at": null,
      "handoff": null
    },
    "5.1": {
      "status": "pending",
      "updated_at": null,
      "handoff": null
    },
    "5.2": {
      "status": "pending",
      "updated_at": null,
      "handoff": null
    },
    "5.3": {
      "status": "complete",
      "updated_at": "2026-07-13T16:55:13.362529+00:00",
      "handoff": "handoffs/5.3.md"
    },
    "5.4": {
      "status": "pending",
      "updated_at": null,
      "handoff": null
    },
    "5.5": {
      "status": "pending",
      "updated_at": null,
      "handoff": null
    },
    "5.6": {
      "status": "pending",
      "updated_at": null,
      "handoff": null
    },
    "6.1": {
      "status": "pending",
      "updated_at": null,
      "handoff": null
    },
    "6.2": {
      "status": "pending",
      "updated_at": null,
      "handoff": null
    },
    "6.3": {
      "status": "pending",
      "updated_at": null,
      "handoff": null
    },
    "6.4": {
      "status": "pending",
      "updated_at": null,
      "handoff": null
    },
    "6.5": {
      "status": "pending",
      "updated_at": null,
      "handoff": null
    },
    "6.6": {
      "status": "complete",
      "updated_at": "2026-07-13T17:04:12.408191+00:00",
      "handoff": "handoffs/6.6.md"
    },
    "7.0": {
      "status": "pending",
      "updated_at": null,
      "handoff": null
    },
    "7.1": {
      "status": "pending",
      "updated_at": null,
      "handoff": null
    },
    "7.2": {
      "status": "complete",
      "updated_at": "2026-07-13T17:08:59.321445+00:00",
      "handoff": "handoffs/7.2.md"
    },
    "7.3": {
      "status": "pending",
      "updated_at": null,
      "handoff": null
    },
    "7.4": {
      "status": "pending",
      "updated_at": null,
      "handoff": null
    },
    "7.5": {
      "status": "pending",
      "updated_at": null,
      "handoff": null
    },
    "8.1": {
      "status": "pending",
      "updated_at": null,
      "handoff": null
    },
    "9.1": {
      "status": "pending",
      "updated_at": null,
      "handoff": null
    },
    "9.2": {
      "status": "pending",
      "updated_at": null,
      "handoff": null
    }
  },
  "phase_gates": {
    "0": {
      "status": "complete",
      "updated_at": "2026-07-13T14:03:17.840943+00:00",
      "handoff": "handoffs/phase-00.md"
    },
    "1": {
      "status": "complete",
      "updated_at": "2026-07-13T17:10:21.981366+00:00",
      "handoff": "handoffs/phase-01.md"
    },
    "2": {
      "status": "pending",
      "updated_at": null,
      "handoff": null
    },
    "3": {
      "status": "pending",
      "updated_at": null,
      "handoff": null
    },
    "4": {
      "status": "pending",
      "updated_at": null,
      "handoff": null
    },
    "5": {
      "status": "pending",
      "updated_at": null,
      "handoff": null
    },
    "6": {
      "status": "pending",
      "updated_at": null,
      "handoff": null
    },
    "7": {
      "status": "pending",
      "updated_at": null,
      "handoff": null
    },
    "8": {
      "status": "pending",
      "updated_at": null,
      "handoff": null
    },
    "9": {
      "status": "pending",
      "updated_at": null,
      "handoff": null
    }
  }
}
